LICENSE
MANIFEST.in
README.rst
setup.cfg
setup.py
versioneer.py
artellapipe/__init__.py
artellapipe/libs/__init__.py
artellapipe/libs/artella/__init__.py
artellapipe/libs/artella/__logging__.ini
artellapipe/libs/artella/__version__.py
artellapipe/libs/artella/_version.py
artellapipe/libs/artella/core/__init__.py
artellapipe/libs/artella/core/artellaclasses.py
artellapipe/libs/artella/core/artellaenterprise.py
artellapipe/libs/artella/core/artellaindie.py
artellapipe/libs/artella/core/artellalib.py
artellapipe_libs_artella.egg-info/PKG-INFO
artellapipe_libs_artella.egg-info/SOURCES.txt
artellapipe_libs_artella.egg-info/dependency_links.txt
artellapipe_libs_artella.egg-info/not-zip-safe
artellapipe_libs_artella.egg-info/requires.txt
artellapipe_libs_artella.egg-info/top_level.txt
tests/__init__.py
tests/test_general.py