Metadata-Version: 2.1
Name: artellapipe-libs-artella
Version: 0.0.10
Summary: Artella libraries for ArtellaPipe
Home-page: https://github.com/ArtellaPipe/artellapipe-libs-artella
Author: Tomas Poveda
Author-email: tpovedatd@gmail.com
License: MIT
Platform: UNKNOWN
Provides-Extra: dev
Provides-Extra: test
